{"version": "1", "data": {"project": {"id": "MzQwMWJkM2Y", "name": "s1046-50_s2012-13_s3026-50"}, "document": {"id": "35d097fe-a58c-4846-87af-e9eae1bce7c3", "name": "3001_046.txt"}, "kinds": ["TOKEN_BASED"], "rows": [[{"content": "Speaker: I guess if I\u2019m giving feedback on um, as far as whatever the end product is to make sure that it is something that all kids would feel comfortable with and not just males or females.", "tokens": ["Speaker", "I", "guess", "if", "I\u2019m", "giving", "feedback", "on", "um,", "as", "far", "as", "whatever", "the", "end", "product", "is", "to", "make", "sure", "that", "it", "is", "something", "that", "all", "kids", "would", "feel", "comfortable", "with", "and", "not", "just", "males", "or", "females."], "metadata": []}], [{"content": "Interviewer: And that lends well in to what I am; this next question is what do you think the take home message from the video should be?", "tokens": ["Interviewer:", "And", "that", "lends", "well", "in", "to", "what", "I", "am;", "this", "next", "question", "is", "what", "do", "you", "think", "the", "take", "home", "message", "from", "the", "video", "should", "be?"], "metadata": []}], [{"content": "Speaker: I would say that the take home message would be like in a way they always go like \u201cask your doctor about so and so\u201d but it would be like a way they show CBT can be to help and that it\u2019s a tool.", "tokens": ["Speaker", "I", "would", "say", "that", "the", "take", "home", "message", "would", "be", "like", "in", "a", "way", "they", "always", "go", "like", "\u201cask", "your", "doctor", "about", "so", "and", "so\u201d", "but", "it", "would", "be", "like", "a", "way", "they", "show", "CBT", "can", "be", "to", "help", "and", "that", "it\u2019s", "a", "tool."], "metadata": []}], [{"content": "You want the child to be able to go like \u201cman I could use that, I could really; that would help me a lot.\u201d", "tokens": ["You", "want", "the", "child", "to", "be", "able", "to", "go", "like", "\u201cman", "I", "could", "use", "that,", "I", "could", "really;", "that", "would", "help", "me", "a", "lot.\u201d"], "metadata": []}], [{"content": "You see, if it gives them an answer as far as something that connects to them and an option I think that that\u2019s kind of what the CBT, for me, needs to be.", "tokens": ["You", "see,", "if", "it", "gives", "them", "an", "answer", "as", "far", "as", "something", "that", "connects", "to", "them", "and", "an", "option", "I", "think", "that", "that\u2019s", "kind", "of", "what", "the", "CBT,", "for", "me,", "needs", "to", "be."], "metadata": []}], [{"content": "It needs to be like \u201cI want to try that; that looks good; it might work\u201d", "tokens": ["It", "needs", "to", "be", "like", "\u201cI", "want", "to", "try", "that;", "that", "looks", "good;", "it", "might", "work\u201d"], "metadata": []}], [{"content": "Speaker: That they\u2019re not alone, um, with working through this.", "tokens": ["Speaker", "That", "they\u2019re", "not", "alone,", "um,", "with", "working", "through", "this."], "metadata": []}], [{"content": "That there\u2019s a team.", "tokens": ["That", "there\u2019s", "a", "team."], "metadata": []}], [{"content": "I know my daughter the feedback she gave me early on was um she didn\u2019t realize how nice everyone would be and helpful everyone would be.", "tokens": ["I", "know", "my", "daughter", "the", "feedback", "she", "gave", "me", "early", "on", "was", "um", "she", "didn\u2019t", "realize", "how", "nice", "everyone", "would", "be", "and", "helpful", "everyone", "would", "be."], "metadata": []}], [{"content": "When somebody\u2019s coming into this there\u2019s a lot of anxiety because I think that um, well I don\u2019t know so I\u2019ll just talk about my daughter\u2019s experience but she thought she was in trouble, she\u2019s here because she\u2019s in trouble.", "tokens": ["When", "somebody\u2019s", "coming", "into", "this", "there\u2019s", "a", "lot", "of", "anxiety", "because", "I", "think", "that", "um,", "well", "I", "don\u2019t", "know", "so", "I\u2019ll", "just", "talk", "about", "my", "daughter\u2019s", "experience", "but", "she", "thought", "she", "was", "in", "trouble,", "she\u2019s", "here", "because", "she\u2019s", "in", "trouble."], "metadata": []}], [{"content": "And so I think letting a person know that there\u2019s a process, this is normal, you\u2019re not doing this alone, um there\u2019s a team of us together, the holding the hand type of approach.", "tokens": ["And", "so", "I", "think", "letting", "a", "person", "know", "that", "there\u2019s", "a", "process,", "this", "is", "normal,", "you\u2019re", "not", "doing", "this", "alone,", "um", "there\u2019s", "a", "team", "of", "us", "together,", "the", "holding", "the", "hand", "type", "of", "approach."], "metadata": []}], [{"content": "Speaker: And the kids themselves, it think because they feel different, they feel strange, or weird, or they have all these emotions and why is it that Billy who\u2019s next to me doesn\u2019t do that.", "tokens": ["Speaker", "And", "the", "kids", "themselves,", "it", "think", "because", "they", "feel", "different,", "they", "feel", "strange,", "or", "weird,", "or", "they", "have", "all", "these", "emotions", "and", "why", "is", "it", "that", "Billy", "who\u2019s", "next", "to", "me", "doesn\u2019t", "do", "that."], "metadata": []}], [{"content": "So it\u2019s like they need to be able to have something to discern to pull them going like \u201cHey Billy may not be like that, but Bobby is\u201d Kids are out there like you, you\u2019re not alone.", "tokens": ["So", "it\u2019s", "like", "they", "need", "to", "be", "able", "to", "have", "something", "to", "discern", "to", "pull", "them", "going", "like", "\u201cHey", "Billy", "may", "not", "be", "like", "that,", "but", "Bobby", "is\u201d", "Kids", "are", "out", "there", "like", "you,", "you\u2019re", "not", "alone."], "metadata": []}], [{"content": "Speaker: Right and like she just didn\u2019t realize and then um when, um I don\u2019t know what they said to her in the first couple sessions but she came away saying \u201cWell I thought it was just me\u201d", "tokens": ["Speaker", "Right", "and", "like", "she", "just", "didn\u2019t", "realize", "and", "then", "um", "when,", "um", "I", "don\u2019t", "know", "what", "they", "said", "to", "her", "in", "the", "first", "couple", "sessions", "but", "she", "came", "away", "saying", "\u201cWell", "I", "thought", "it", "was", "just", "me\u201d"], "metadata": []}], [{"content": "Speaker: You do because I am a person who has that so I can go like you just feel like wow you\u2019re just so off and everybody else is so right and you feel so different.", "tokens": ["Speaker", "You", "do", "because", "I", "am", "a", "person", "who", "has", "that", "so", "I", "can", "go", "like", "you", "just", "feel", "like", "wow", "you\u2019re", "just", "so", "off", "and", "everybody", "else", "is", "so", "right", "and", "you", "feel", "so", "different."], "metadata": []}], [{"content": "If you can make that kid go like \u201cwow I\u2019m not that different and there people like me and they can help me\u201d Get that message to them.", "tokens": ["If", "you", "can", "make", "that", "kid", "go", "like", "\u201cwow", "I\u2019m", "not", "that", "different", "and", "there", "people", "like", "me", "and", "they", "can", "help", "me\u201d", "Get", "that", "message", "to", "them."], "metadata": []}], [{"content": "Speaker: Right and like you know a sense of hope that there is a process and if you are willing to work through the process you can feel more comfortable and not feel as much anxiety about it.", "tokens": ["Speaker", "Right", "and", "like", "you", "know", "a", "sense", "of", "hope", "that", "there", "is", "a", "process", "and", "if", "you", "are", "willing", "to", "work", "through", "the", "process", "you", "can", "feel", "more", "comfortable", "and", "not", "feel", "as", "much", "anxiety", "about", "it."], "metadata": []}], [{"content": "Not alone", "tokens": ["Not", "alone"], "metadata": []}], [{"content": "Interviewer: Ok.", "tokens": ["Interviewer:", "Ok."], "metadata": []}], [{"content": "And finally is there anything that I missed or anything important that I didn\u2019t ask about that you think is relevant to making CBT videos?", "tokens": ["And", "finally", "is", "there", "anything", "that", "I", "missed", "or", "anything", "important", "that", "I", "didn\u2019t", "ask", "about", "that", "you", "think", "is", "relevant", "to", "making", "CBT", "videos?"], "metadata": []}], [{"content": "Speaker: I don\u2019t have any additional comment.", "tokens": ["Speaker", "I", "don\u2019t", "have", "any", "additional", "comment."], "metadata": []}], [{"content": "Speaker: I think it\u2019s all basically it\u2019s just the videos that show that there\u2019s help for the kids, you know, it\u2019s an option and let the parents know as well as the kids that just the education of it because some people may not have that out there of \u201cit\u2019s an option\u201d.", "tokens": ["Speaker", "I", "think", "it\u2019s", "all", "basically", "it\u2019s", "just", "the", "videos", "that", "show", "that", "there\u2019s", "help", "for", "the", "kids,", "you", "know,", "it\u2019s", "an", "option", "and", "let", "the", "parents", "know", "as", "well", "as", "the", "kids", "that", "just", "the", "education", "of", "it", "because", "some", "people", "may", "not", "have", "that", "out", "there", "of", "\u201cit\u2019s", "an", "option\u201d."], "metadata": []}], [{"content": "And that\u2019s the big point it\u2019s an option and let the people know \u201chey I\u2019m going to try it\u201d", "tokens": ["And", "that\u2019s", "the", "big", "point", "it\u2019s", "an", "option", "and", "let", "the", "people", "know", "\u201chey", "I\u2019m", "going", "to", "try", "it\u201d"], "metadata": []}], [{"content": "Speaker: How long were you going to make the video, were you all targeting; have you all thought about how long you\u2019re going to make the video for?", "tokens": ["Speaker", "How", "long", "were", "you", "going", "to", "make", "the", "video,", "were", "you", "all", "targeting;", "have", "you", "all", "thought", "about", "how", "long", "you\u2019re", "going", "to", "make", "the", "video", "for?"], "metadata": []}], [{"content": "The length of it.", "tokens": ["The", "length", "of", "it."], "metadata": []}]], "labelerInfo": {"id": 7436, "email": "smoeller@ufl.edu", "displayName": "Sarah Moeller"}, "labelSets": [{"name": "HD tagset", "index": 0, "labelItems": [{"id": "zynoJJigppWPaLrXIbl7r", "labelName": "Incomplete Thought", "parentId": null, "color": "#ffc826"}, {"id": "CVVUxC8SvzFkW325Jv13R", "labelName": "Self Correction", "parentId": null, "color": "#33cc99"}, {"id": "yJ2I5X2l397BXK0vkQOqb", "labelName": "Clarification", "parentId": null, "color": "#3370cc"}, {"id": "-JMh1Z2QiTPafZ-k12D4R", "labelName": "Generic Disfluency", "parentId": null, "color": "#ff8000"}, {"id": "zNhzFxWreupeViuWpVQbm", "labelName": "Misspeak", "parentId": null, "color": "#df3920"}, {"id": "VBS0Kk5Mwre1tPCapxA3k", "labelName": "Overlap", "parentId": null, "color": "#9933cc"}, {"id": "nmDmE8yCiIjn1v0WJrgTj", "labelName": "Unclear", "parentId": null, "color": null}], "leafOnlyOption": false}], "spanLabels": [], "arrowLabels": [], "boundingBoxLabels": [], "timeLabels": [], "comments": [], "url": "datasaur://static/7436/6811f6c0-8034-4115-847b-0a105b795654.txt", "rowAnswers": [], "documentAnswers": []}, "rows": [{"content": "Speaker: I guess if I\u2019m giving feedback on um, as far as whatever the end product is to make sure that it is something that all kids would feel comfortable with and not just males or females.", "tokens": ["Speaker", "I", "guess", "if", "I\u2019m", "giving", "feedback", "on", "um,", "as", "far", "as", "whatever", "the", "end", "product", "is", "to", "make", "sure", "that", "it", "is", "something", "that", "all", "kids", "would", "feel", "comfortable", "with", "and", "not", "just", "males", "or", "females."], "metadata": []}, {"content": "Interviewer: And that lends well in to what I am; this next question is what do you think the take home message from the video should be?", "tokens": ["Interviewer:", "And", "that", "lends", "well", "in", "to", "what", "I", "am;", "this", "next", "question", "is", "what", "do", "you", "think", "the", "take", "home", "message", "from", "the", "video", "should", "be?"], "metadata": []}, {"content": "Speaker: I would say that the take home message would be like in a way they always go like \u201cask your doctor about so and so\u201d but it would be like a way they show CBT can be to help and that it\u2019s a tool.", "tokens": ["Speaker", "I", "would", "say", "that", "the", "take", "home", "message", "would", "be", "like", "in", "a", "way", "they", "always", "go", "like", "\u201cask", "your", "doctor", "about", "so", "and", "so\u201d", "but", "it", "would", "be", "like", "a", "way", "they", "show", "CBT", "can", "be", "to", "help", "and", "that", "it\u2019s", "a", "tool."], "metadata": []}, {"content": "You want the child to be able to go like \u201cman I could use that, I could really; that would help me a lot.\u201d", "tokens": ["You", "want", "the", "child", "to", "be", "able", "to", "go", "like", "\u201cman", "I", "could", "use", "that,", "I", "could", "really;", "that", "would", "help", "me", "a", "lot.\u201d"], "metadata": []}, {"content": "You see, if it gives them an answer as far as something that connects to them and an option I think that that\u2019s kind of what the CBT, for me, needs to be.", "tokens": ["You", "see,", "if", "it", "gives", "them", "an", "answer", "as", "far", "as", "something", "that", "connects", "to", "them", "and", "an", "option", "I", "think", "that", "that\u2019s", "kind", "of", "what", "the", "CBT,", "for", "me,", "needs", "to", "be."], "metadata": []}, {"content": "It needs to be like \u201cI want to try that; that looks good; it might work\u201d", "tokens": ["It", "needs", "to", "be", "like", "\u201cI", "want", "to", "try", "that;", "that", "looks", "good;", "it", "might", "work\u201d"], "metadata": []}, {"content": "Speaker: That they\u2019re not alone, um, with working through this.", "tokens": ["Speaker", "That", "they\u2019re", "not", "alone,", "um,", "with", "working", "through", "this."], "metadata": []}, {"content": "That there\u2019s a team.", "tokens": ["That", "there\u2019s", "a", "team."], "metadata": []}, {"content": "I know my daughter the feedback she gave me early on was um she didn\u2019t realize how nice everyone would be and helpful everyone would be.", "tokens": ["I", "know", "my", "daughter", "the", "feedback", "she", "gave", "me", "early", "on", "was", "um", "she", "didn\u2019t", "realize", "how", "nice", "everyone", "would", "be", "and", "helpful", "everyone", "would", "be."], "metadata": []}, {"content": "When somebody\u2019s coming into this there\u2019s a lot of anxiety because I think that um, well I don\u2019t know so I\u2019ll just talk about my daughter\u2019s experience but she thought she was in trouble, she\u2019s here because she\u2019s in trouble.", "tokens": ["When", "somebody\u2019s", "coming", "into", "this", "there\u2019s", "a", "lot", "of", "anxiety", "because", "I", "think", "that", "um,", "well", "I", "don\u2019t", "know", "so", "I\u2019ll", "just", "talk", "about", "my", "daughter\u2019s", "experience", "but", "she", "thought", "she", "was", "in", "trouble,", "she\u2019s", "here", "because", "she\u2019s", "in", "trouble."], "metadata": []}, {"content": "And so I think letting a person know that there\u2019s a process, this is normal, you\u2019re not doing this alone, um there\u2019s a team of us together, the holding the hand type of approach.", "tokens": ["And", "so", "I", "think", "letting", "a", "person", "know", "that", "there\u2019s", "a", "process,", "this", "is", "normal,", "you\u2019re", "not", "doing", "this", "alone,", "um", "there\u2019s", "a", "team", "of", "us", "together,", "the", "holding", "the", "hand", "type", "of", "approach."], "metadata": []}, {"content": "Speaker: And the kids themselves, it think because they feel different, they feel strange, or weird, or they have all these emotions and why is it that Billy who\u2019s next to me doesn\u2019t do that.", "tokens": ["Speaker", "And", "the", "kids", "themselves,", "it", "think", "because", "they", "feel", "different,", "they", "feel", "strange,", "or", "weird,", "or", "they", "have", "all", "these", "emotions", "and", "why", "is", "it", "that", "Billy", "who\u2019s", "next", "to", "me", "doesn\u2019t", "do", "that."], "metadata": []}, {"content": "So it\u2019s like they need to be able to have something to discern to pull them going like \u201cHey Billy may not be like that, but Bobby is\u201d Kids are out there like you, you\u2019re not alone.", "tokens": ["So", "it\u2019s", "like", "they", "need", "to", "be", "able", "to", "have", "something", "to", "discern", "to", "pull", "them", "going", "like", "\u201cHey", "Billy", "may", "not", "be", "like", "that,", "but", "Bobby", "is\u201d", "Kids", "are", "out", "there", "like", "you,", "you\u2019re", "not", "alone."], "metadata": []}, {"content": "Speaker: Right and like she just didn\u2019t realize and then um when, um I don\u2019t know what they said to her in the first couple sessions but she came away saying \u201cWell I thought it was just me\u201d", "tokens": ["Speaker", "Right", "and", "like", "she", "just", "didn\u2019t", "realize", "and", "then", "um", "when,", "um", "I", "don\u2019t", "know", "what", "they", "said", "to", "her", "in", "the", "first", "couple", "sessions", "but", "she", "came", "away", "saying", "\u201cWell", "I", "thought", "it", "was", "just", "me\u201d"], "metadata": []}, {"content": "Speaker: You do because I am a person who has that so I can go like you just feel like wow you\u2019re just so off and everybody else is so right and you feel so different.", "tokens": ["Speaker", "You", "do", "because", "I", "am", "a", "person", "who", "has", "that", "so", "I", "can", "go", "like", "you", "just", "feel", "like", "wow", "you\u2019re", "just", "so", "off", "and", "everybody", "else", "is", "so", "right", "and", "you", "feel", "so", "different."], "metadata": []}, {"content": "If you can make that kid go like \u201cwow I\u2019m not that different and there people like me and they can help me\u201d Get that message to them.", "tokens": ["If", "you", "can", "make", "that", "kid", "go", "like", "\u201cwow", "I\u2019m", "not", "that", "different", "and", "there", "people", "like", "me", "and", "they", "can", "help", "me\u201d", "Get", "that", "message", "to", "them."], "metadata": []}, {"content": "Speaker: Right and like you know a sense of hope that there is a process and if you are willing to work through the process you can feel more comfortable and not feel as much anxiety about it.", "tokens": ["Speaker", "Right", "and", "like", "you", "know", "a", "sense", "of", "hope", "that", "there", "is", "a", "process", "and", "if", "you", "are", "willing", "to", "work", "through", "the", "process", "you", "can", "feel", "more", "comfortable", "and", "not", "feel", "as", "much", "anxiety", "about", "it."], "metadata": []}, {"content": "Not alone", "tokens": ["Not", "alone"], "metadata": []}, {"content": "Interviewer: Ok.", "tokens": ["Interviewer:", "Ok."], "metadata": []}, {"content": "And finally is there anything that I missed or anything important that I didn\u2019t ask about that you think is relevant to making CBT videos?", "tokens": ["And", "finally", "is", "there", "anything", "that", "I", "missed", "or", "anything", "important", "that", "I", "didn\u2019t", "ask", "about", "that", "you", "think", "is", "relevant", "to", "making", "CBT", "videos?"], "metadata": []}, {"content": "Speaker: I don\u2019t have any additional comment.", "tokens": ["Speaker", "I", "don\u2019t", "have", "any", "additional", "comment."], "metadata": []}, {"content": "Speaker: I think it\u2019s all basically it\u2019s just the videos that show that there\u2019s help for the kids, you know, it\u2019s an option and let the parents know as well as the kids that just the education of it because some people may not have that out there of \u201cit\u2019s an option\u201d.", "tokens": ["Speaker", "I", "think", "it\u2019s", "all", "basically", "it\u2019s", "just", "the", "videos", "that", "show", "that", "there\u2019s", "help", "for", "the", "kids,", "you", "know,", "it\u2019s", "an", "option", "and", "let", "the", "parents", "know", "as", "well", "as", "the", "kids", "that", "just", "the", "education", "of", "it", "because", "some", "people", "may", "not", "have", "that", "out", "there", "of", "\u201cit\u2019s", "an", "option\u201d."], "metadata": []}, {"content": "And that\u2019s the big point it\u2019s an option and let the people know \u201chey I\u2019m going to try it\u201d", "tokens": ["And", "that\u2019s", "the", "big", "point", "it\u2019s", "an", "option", "and", "let", "the", "people", "know", "\u201chey", "I\u2019m", "going", "to", "try", "it\u201d"], "metadata": []}, {"content": "Speaker: How long were you going to make the video, were you all targeting; have you all thought about how long you\u2019re going to make the video for?", "tokens": ["Speaker", "How", "long", "were", "you", "going", "to", "make", "the", "video,", "were", "you", "all", "targeting;", "have", "you", "all", "thought", "about", "how", "long", "you\u2019re", "going", "to", "make", "the", "video", "for?"], "metadata": []}, {"content": "The length of it.", "tokens": ["The", "length", "of", "it."], "metadata": []}]}