{"version":"1","data":{"project":{"id":"NTE3MmUyODM","name":"s1_21-27_s2_1-3"},"document":{"id":"13e0ab2e-7057-41d4-ae89-963ce1ea7ef7","name":"027_313.txt"},"kinds":["TOKEN_BASED"],"rows":[[{"content":"If the Coast Guard son...","tokens":["If","the","Coast","Guard","son..."],"metadata":[]}],[{"content":"We used to have their children a lot.","tokens":["We","used","to","have","their","children","a","lot."],"metadata":[]}],[{"content":"We don't know because of COVID, but he would call and say, \"Can I bring the kids up for a few days?\" They can walk into their playroom and everything is arranged so that they can play right there.","tokens":["We","don't","know","because","of","COVID,","but","he","would","call","and","say,","\"Can","I","bring","the","kids","up","for","a","few","days?\"","They","can","walk","into","their","playroom","and","everything","is","arranged","so","that","they","can","play","right","there."],"metadata":[]}],[{"content":"Then underneath that, I have two bedrooms.","tokens":["Then","underneath","that,","I","have","two","bedrooms."],"metadata":[]}],[{"content":"The one is the guest bedroom I was talking about and the other one is a smaller bedroom with a twin bed.","tokens":["The","one","is","the","guest","bedroom","I","was","talking","about","and","the","other","one","is","a","smaller","bedroom","with","a","twin","bed."],"metadata":[]}],[{"content":"That's where my grandchildren stay.","tokens":["That's","where","my","grandchildren","stay."],"metadata":[]}],[{"content":"There's three of them so they have those two bedrooms and a bath.","tokens":["There's","three","of","them","so","they","have","those","two","bedrooms","and","a","bath."],"metadata":[]}],[{"content":"Then underneath that is another...","tokens":["Then","underneath","that","is","another..."],"metadata":[]}],[{"content":"It's a music room.","tokens":["It's","a","music","room."],"metadata":[]}],[{"content":"It's where my son used to play with his band.","tokens":["It's","where","my","son","used","to","play","with","his","band."],"metadata":[]}],[{"content":"There's still two drum sets down there and a lot of music sound equipment that I don't know what to do with and I would like to sell, but I don't know what I have.","tokens":["There's","still","two","drum","sets","down","there","and","a","lot","of","music","sound","equipment","that","I","don't","know","what","to","do","with","and","I","would","like","to","sell,","but","I","don't","know","what","I","have."],"metadata":[]}],[{"content":"I took it apart to move it, and then I couldn't put it back together.","tokens":["I","took","it","apart","to","move","it,","and","then","I","couldn't","put","it","back","together."],"metadata":[]}],[{"content":"So now we don't have surround sound or anything.","tokens":["So","now","we","don't","have","surround","sound","or","anything."],"metadata":[]}],[{"content":"There's a couch that can pull out to a double bed down there.","tokens":["There's","a","couch","that","can","pull","out","to","a","double","bed","down","there."],"metadata":[]}],[{"content":"Then I can have company stay there too.","tokens":["Then","I","can","have","company","stay","there","too."],"metadata":[]}],[{"content":"What we're putting on is a sun room that will come off of the eBay room and the dining room with entrances to both.","tokens":["What","we're","putting","on","is","a","sun","room","that","will","come","off","of","the","eBay","room","and","the","dining","room","with","entrances","to","both."],"metadata":[]}],[{"content":"That will be 20 feet by 14 feet.","tokens":["That","will","be","20","feet","by","14","feet."],"metadata":[]}],[{"content":"I can move some of the furniture.","tokens":["I","can","move","some","of","the","furniture."],"metadata":[]}],[{"content":"I don't go out and buy anything new anyway, anytime.","tokens":["I","don't","go","out","and","buy","anything","new","anyway,","anytime."],"metadata":[]}],[{"content":"I buy from Craigslist if I need something.","tokens":["I","buy","from","Craigslist","if","I","need","something."],"metadata":[]}],[{"content":"I think when Jerry moved in, he bought us a new mattress, and that's the only new thing that has come into the house.","tokens":["I","think","when","Jerry","moved","in,","he","bought","us","a","new","mattress,","and","that's","the","only","new","thing","that","has","come","into","the","house."],"metadata":[]}],[{"content":"When my parents died, I inherited a lot of their antiques, so I have plenty of furniture to move into the new room [crosstalk 00:36:03] the house.","tokens":["When","my","parents","died,","I","inherited","a","lot","of","their","antiques,","so","I","have","plenty","of","furniture","to","move","into","the","new","room","[crosstalk","00:36:03]","the","house."],"metadata":[]}],[{"content":"Then we have another house in Florida.","tokens":["Then","we","have","another","house","in","Florida."],"metadata":[]}],[{"content":"Do you want that one too?","tokens":["Do","you","want","that","one","too?"],"metadata":[]}],[{"content":"Interviewer:","tokens":["Interviewer:"],"metadata":[]}],[{"content":"Do you spend a significant amount of your time there?","tokens":["Do","you","spend","a","significant","amount","of","your","time","there?"],"metadata":[]}],[{"content":"Participant 27:","tokens":["Participant","27:"],"metadata":[]}],[{"content":"Four to five months out of the year.","tokens":["Four","to","five","months","out","of","the","year."],"metadata":[]}],[{"content":"Interviewer:","tokens":["Interviewer:"],"metadata":[]}],[{"content":"Okay.","tokens":["Okay."],"metadata":[]}],[{"content":"Do you have a similar amount of things down there?","tokens":["Do","you","have","a","similar","amount","of","things","down","there?"],"metadata":[]}],[{"content":"Participant 27:","tokens":["Participant","27:"],"metadata":[]}],[{"content":"I do collect things down there, but what I have down there, I have purchased down there like at flea markets and stuff.","tokens":["I","do","collect","things","down","there,","but","what","I","have","down","there,","I","have","purchased","down","there","like","at","flea","markets","and","stuff."],"metadata":[]}],[{"content":"I am Mrs. Claus at Hersheypark for 21 years, so I collect Mrs. Clauses.","tokens":["I","am","Mrs.","Claus","at","Hersheypark","for","21","years,","so","I","collect","Mrs.","Clauses."],"metadata":[]}],[{"content":"There are a lot of Mrs. Clauses down there and some pictures, but pretty much other than that, it's basically...","tokens":["There","are","a","lot","of","Mrs.","Clauses","down","there","and","some","pictures,","but","pretty","much","other","than","that,","it's","basically..."],"metadata":[]}],[{"content":"It's a one bedroom, one bath house on the beach.","tokens":["It's","a","one","bedroom,","one","bath","house","on","the","beach."],"metadata":[]}],[{"content":"We have a trailer that sleeps 12 and that's where our guests stay.","tokens":["We","have","a","trailer","that","sleeps","12","and","that's","where","our","guests","stay."],"metadata":[]}],[{"content":"I do have a lot of stuff there, but it's not where I collect my stuff.","tokens":["I","do","have","a","lot","of","stuff","there,","but","it's","not","where","I","collect","my","stuff."],"metadata":[]}],[{"content":"Interviewer:","tokens":["Interviewer:"],"metadata":[]}],[{"content":"Gotcha.","tokens":["Gotcha."],"metadata":[]}],[{"content":"Thinking about your place in Pennsylvania, where you keep most of your stuff, how important are your things for you to feel at home?","tokens":["Thinking","about","your","place","in","Pennsylvania,","where","you","keep","most","of","your","stuff,","how","important","are","your","things","for","you","to","feel","at","home?"],"metadata":[]}],[{"content":"Participant 27:","tokens":["Participant","27:"],"metadata":[]}],[{"content":"Extremely important.","tokens":["Extremely","important."],"metadata":[]}]],"labelerInfo":{"id":7665,"email":"a.eads@ufl.edu","displayName":"Eads, Ashley J."},"labelSets":[{"name":"HD tagset","index":0,"labelItems":[{"id":"zynoJJigppWPaLrXIbl7r","labelName":"Incomplete Thought","parentId":null,"color":"#ffc826"},{"id":"CVVUxC8SvzFkW325Jv13R","labelName":"Self Correction","parentId":null,"color":"#33cc99"},{"id":"yJ2I5X2l397BXK0vkQOqb","labelName":"Clarification","parentId":null,"color":"#3370cc"},{"id":"-JMh1Z2QiTPafZ-k12D4R","labelName":"Generic Disfluency","parentId":null,"color":"#ff8000"},{"id":"zNhzFxWreupeViuWpVQbm","labelName":"Misspeak","parentId":null,"color":"#df3920"},{"id":"VBS0Kk5Mwre1tPCapxA3k","labelName":"Overlap","parentId":null,"color":"#9933cc"},{"id":"nmDmE8yCiIjn1v0WJrgTj","labelName":"Unclear","parentId":null,"color":null}],"leafOnlyOption":false}],"spanLabels":[{"id":"1693557130","labelSetIndex":0,"labeledBy":"LABELER","labeledByUserId":7665,"acceptedByUserId":null,"rejectedByUserId":null,"layer":0,"counter":0,"status":"LABELED","hashCode":"SPAN:yJ2I5X2l397BXK0vkQOqb:0:0:0:0:0:0:0:4:5:0:undefined:undefined","labelName":"yJ2I5X2l397BXK0vkQOqb","labelItem":{"id":"yJ2I5X2l397BXK0vkQOqb","labelName":"Clarification","parentId":null,"color":"#3370cc"},"textPosition":{"start":{"row":0,"column":0,"tokenIndex":0,"charIndex":0},"end":{"row":0,"column":0,"tokenIndex":4,"charIndex":5}},"confidenceScore":null},{"id":"1693557133","labelSetIndex":0,"labeledBy":"LABELER","labeledByUserId":7665,"acceptedByUserId":null,"rejectedByUserId":null,"layer":0,"counter":0,"status":"LABELED","hashCode":"SPAN:-JMh1Z2QiTPafZ-k12D4R:0:7:0:0:0:7:0:4:9:0:undefined:undefined","labelName":"-JMh1Z2QiTPafZ-k12D4R","labelItem":{"id":"-JMh1Z2QiTPafZ-k12D4R","labelName":"Generic Disfluency","parentId":null,"color":"#ff8000"},"textPosition":{"start":{"row":7,"column":0,"tokenIndex":0,"charIndex":0},"end":{"row":7,"column":0,"tokenIndex":4,"charIndex":9}},"confidenceScore":null},{"id":"1693557136","labelSetIndex":0,"labeledBy":"LABELER","labeledByUserId":7665,"acceptedByUserId":null,"rejectedByUserId":null,"layer":0,"counter":0,"status":"ACCEPTED","hashCode":"SPAN:zynoJJigppWPaLrXIbl7r:0:34:0:18:0:34:0:19:11:0:undefined:undefined","labelName":"zynoJJigppWPaLrXIbl7r","labelItem":{"id":"zynoJJigppWPaLrXIbl7r","labelName":"Incomplete Thought","parentId":null,"color":"#ffc826"},"textPosition":{"start":{"row":34,"column":0,"tokenIndex":18,"charIndex":0},"end":{"row":34,"column":0,"tokenIndex":19,"charIndex":11}},"confidenceScore":null}],"arrowLabels":[],"boundingBoxLabels":[],"timeLabels":[],"comments":[],"url":"datasaur://static/7436/68e198fa-9a50-4227-a239-768f0e02aeaf.txt","rowAnswers":[],"documentAnswers":[]}}
